{
    "day": 3,
    "words": [
        {
            "english": "ancient",
            "korean": "고대의"
        },
        {
            "english": "era",
            "korean": "시대"
        },
        {
            "english": "existing",
            "korean": "기존의, 존재하는"
        },
        {
            "english": "combine",
            "korean": "결합하다, 섞다"
        },
        {
            "english": "ethnic",
            "korean": "민족의"
        },
        {
            "english": "popular",
            "korean": "인기있는, 대중적인"
        },
        {
            "english": "population",
            "korean": "인구"
        },
        {
            "english": "in person",
            "korean": "직접"
        },
        {
            "english": "personal",
            "korean": "개인의"
        },
        {
            "english": "public",
            "korean": "공공의"
        },
        {
            "english": "candidate",
            "korean": "후보"
        },
        {
            "english": "vote",
            "korean": "표, 투표, 투표하다"
        },
        {
            "english": "elect",
            "korean": "선출하다"
        },
        {
            "english": "election",
            "korean": "선거"
        },
        {
            "english": "democracy",
            "korean": "민주주의"
        },
        {
            "english": "obstacle",
            "korean": "장애물"
        },
        {
            "english": "difficulty",
            "korean": "어려움"
        },
        {
            "english": "hardship",
            "korean": "어려움, 고난"
        },
        {
            "english": "obtain",
            "korean": "얻다"
        },
        {
            "english": "gain",
            "korean": "얻다, 획득하다"
        },
        {
            "english": "favorite",
            "korean": "호의적인"
        },
        {
            "english": "likable",
            "korean": "호감이 가는"
        },
        {
            "english": "dislike",
            "korean": "싫어하다"
        },
        {
            "english": "fail",
            "korean": "실패하다"
        },
        {
            "english": "succeed",
            "korean": "성공하다"
        },
        {
            "english": "success",
            "korean": "성공"
        },
        {
            "english": "renowned",
            "korean": "유명한"
        },
        {
            "english": "well-known",
            "korean": "잘 알려진"
        },
        {
            "english": "permit",
            "korean": "허락하다"
        },
        {
            "english": "permission",
            "korean": "허락, 허가"
        },
        {
            "english": "temporary",
            "korean": "일시적인, 임시의"
        },
        {
            "english": "permanent",
            "korean": "영구적인, 영원한"
        },
        {
            "english": "eternal",
            "korean": "영원한, 불변의"
        },
        {
            "english": "constant",
            "korean": "일정한, 불변의"
        },
        {
            "english": "regular",
            "korean": "규칙적인, 정기적인"
        },
        {
            "english": "steady",
            "korean": "안정적인, 흔들리지 않는"
        },
        {
            "english": "fluctuate",
            "korean": "변동하다, 오르내리다"
        },
        {
            "english": "relationship",
            "korean": "관계"
        },
        {
            "english": "elaborate",
            "korean": "정교한, 정성 들여 만든"
        },
        {
            "english": "sophisticated",
            "korean": "정교한, 세련된"
        },
        {
            "english": "exhibit",
            "korean": "전시하다, 나타내다"
        },
        {
            "english": "mammal",
            "korean": "포유류"
        },
        {
            "english": "flourish",
            "korean": "번성하다, 번영하다"
        },
        {
            "english": "extinct",
            "korean": "멸종된"
        },
        {
            "english": "fossil",
            "korean": "화석"
        },
        {
            "english": "foster",
            "korean": "증진시키다, 촉진하다"
        },
        {
            "english": "facilitate",
            "korean": "돕다"
        },
        {
            "english": "get used to A",
            "korean": "A에 익숙해지다"
        },
        {
            "english": "familiar",
            "korean": "익숙한, 친숙한"
        },
        {
            "english": "alien",
            "korean": "외계인, 이질적인"
        }
    ]
}